pb_job_manager-0.2.2.dist-info/pbr.json
pb_job_manager-0.2.2.dist-info/top_level.txt
pb_job_manager-0.2.2.dist-info/WHEEL
pb_job_manager-0.2.2.dist-info/METADATA
pb_job_manager-0.2.2.dist-info/metadata.json
pb_job_manager-0.2.2.dist-info/RECORD
pb_job_manager-0.2.2.dist-info/DESCRIPTION.rst
pb_job_manager/__init__.py
