Metadata-Version: 2.0
Name: pb-job-manager
Version: 0.2.2
Summary: A utility class to run plumbum commands concurrently
Home-page: https://github.com/mbarkhau/pb-job-manager/
Author: Manuel Barkhau
Author-email: mbarkhau@gmail.com
License: BSD License
Keywords: plumbum,shell,popen,process,subprocess,multiprocess
Platform: UNKNOWN
Classifier: Development Status :: 4 - Beta
Classifier: Environment :: Console
Classifier: Intended Audience :: Developers
Classifier: License :: OSI Approved :: BSD License
Classifier: Operating System :: MacOS :: MacOS X
Classifier: Operating System :: POSIX
Classifier: Programming Language :: Python
Classifier: Programming Language :: Python :: 2
Classifier: Programming Language :: Python :: 3
Classifier: Topic :: Utilities
Requires-Dist: plumbum (>=1.4)
Provides-Extra: dev
Requires-Dist: pytest; extra == 'dev'
Requires-Dist: wheel; extra == 'dev'
